pyglobal/__init__.py
pyglobal/__init__.pyc
pyglobal/__meta__.py
pyglobal/__meta__.pyc
pyglobal/cglobal.cp36-win32.pyd
pyglobal/cglobal.cp36-win_amd64.pyd
pyglobal/cglobal.cp37-win32.pyd
pyglobal/cglobal.cp37-win_amd64.pyd
pyglobal/cglobal.cp38-win32.pyd
pyglobal/cglobal.cp38-win_amd64.pyd
pyglobal/__pycache__/__init__.cpython-34.pyc
pyglobal/__pycache__/__init__.cpython-36.pyc
pyglobal/__pycache__/__init__.cpython-37.pyc
pyglobal/__pycache__/__init__.cpython-38.pyc
pyglobal/__pycache__/__meta__.cpython-34.pyc
pyglobal/__pycache__/__meta__.cpython-36.pyc
pyglobal/__pycache__/__meta__.cpython-37.pyc
pyglobal/__pycache__/__meta__.cpython-38.pyc
pyglobal-0.0.1.dist-info/LICENSE
pyglobal-0.0.1.dist-info/METADATA
pyglobal-0.0.1.dist-info/WHEEL
pyglobal-0.0.1.dist-info/top_level.txt
pyglobal-0.0.1.dist-info/RECORD
