Metadata-Version: 1.1
Name: pyglobal
Version: 0.0.1
Summary: Global accessors for things like settings. This could be used across applications and modules to share data.
Home-page: https://github.com/justengel/pyglobal
Author: Justin Engel
Author-email: jtengel08@gmail.com
License: MIT
Download-URL: https://github.com/justengel/pyglobal/archive/v0.0.1.tar.gz
Keywords: global settings
Platform: any
Classifier: Programming Language :: Python
Classifier: Programming Language :: Python :: 3
Classifier: Operating System :: OS Independent
